{
 "charts": [
  {
   "chart_name": "Visits Created",
   "label": "Visits Created"
  }
 ],
 "content": "[{\"id\":\"hdr1\",\"type\":\"header\",\"data\":{\"text\":\"<span class=\\\"h5\\\"><b>VISITS</b></span>\",\"col\":12}},{\"id\":\"sp1\",\"type\":\"spacer\",\"data\":{\"col\":12}},{\"id\":\"cb1\",\"type\":\"custom_block\",\"data\":{\"custom_block_name\":\"Visits KPI Panel\",\"col\":12}},{\"id\":\"sp1a\",\"type\":\"spacer\",\"data\":{\"col\":12}},{\"id\":\"ch1\",\"type\":\"chart\",\"data\":{\"chart_name\":\"Visits Created\",\"col\":12}},{\"id\":\"sp1b\",\"type\":\"spacer\",\"data\":{\"col\":12}},{\"id\":\"ncF\",\"type\":\"number_card\",\"data\":{\"number_card_name\":\"Overdue Routine Visits\",\"col\":3}},{\"id\":\"sp2\",\"type\":\"spacer\",\"data\":{\"col\":12}},{\"id\":\"p1\",\"type\":\"paragraph\",\"data\":{\"text\":\"<b>SHORTCUTS</b>\",\"col\":12}},{\"id\":\"sh1\",\"type\":\"shortcut\",\"data\":{\"shortcut_name\":\"Visit\",\"col\":3}},{\"id\":\"sh3\",\"type\":\"shortcut\",\"data\":{\"shortcut_name\":\"Weekly Schedule\",\"col\":3}},{\"id\":\"sh4\",\"type\":\"shortcut\",\"data\":{\"shortcut_name\":\"Visit Overview\",\"col\":3}}]",
 "creation": "2025-11-03 00:06:47.715420",
 "custom_blocks": [
  {
   "custom_block_name": "Visits KPI Panel",
   "label": "Visits KPI Panel"
  }
 ],
 "docstatus": 0,
 "doctype": "Workspace",
 "hide_custom": 0,
 "icon": "map-pin",
 "idx": 0,
 "indicator_color": "green",
 "is_hidden": 0,
 "label": "Visits",
 "links": [],
 "modified": "2025-11-04 11:05:20.542526",
 "modified_by": "Administrator",
 "module": "Visit Management",
 "name": "Visits",
 "number_cards": [
  {
   "label": "Overdue Routine Visits",
   "number_card_name": "Overdue Routine Visits"
  }
 ],
 "owner": "Administrator",
 "public": 1,
 "quick_lists": [],
 "roles": [],
 "sequence_id": 0.0,
 "shortcuts": [
  {
   "color": "Grey",
   "doc_view": "List",
   "label": "Visit",
   "link_to": "Visit",
   "stats_filter": "[]",
   "type": "DocType"
  },
  {
   "color": "Grey",
   "doc_view": "List",
   "label": "Weekly Schedule",
   "link_to": "Weekly Schedule",
   "stats_filter": "[]",
   "type": "DocType"
  },
  {
   "color": "Grey",
   "doc_view": "",
   "label": "Visit Overview",
   "link_to": "Visit Overview",
   "type": "Dashboard"
  }
 ],
 "title": "Visits"
}
